traj/__init__.py
traj/array.py
traj/fd.py
traj/potential.py
traj/propagate.py
traj/root.py
traj/sample.py
traj/tof.py
traj/tri.py
traj/wf.py
traj-0.0.6.dist-info/LICENSE.txt
traj-0.0.6.dist-info/METADATA
traj-0.0.6.dist-info/WHEEL
traj-0.0.6.dist-info/top_level.txt
traj-0.0.6.dist-info/RECORD
