Metadata-Version: 2.1
Name: traj
Version: 0.0.6
Summary: Bohmian trajectory
Author: sahn
Author-email: jam31118@gmail.com
Classifier: Programming Language :: Python :: 3
Classifier: License :: OSI Approved :: MIT License
Requires-Python: >=3.6
License-File: LICENSE.txt
